{
  "cctv0": { "on": [], "off": [] },
  "cctv1": { "on": [], "off": [] },
  "cctv2": {
    "on": ["1h 47m 9s", "2m 4s", "3h 58m 54s", "5h 9m 4s", "1m 4s", "59m 54s"],
    "off": ["44s", "44s", "54s", "14s", "24s", "14s"]
  },
  "cctv3": { "on": [], "off": [] },
  "phone": {
    "on": [
      "2h 57m 40s",
      "4h 59m 55s",
      "3m 15s",
      "35m 5s",
      "25m 16s",
      "2m 24s",
      "8m 4s",
      "4h 12m 55s",
      "45s",
      "45s"
    ],
    "off": [
      "5h 30m 45s",
      "1m 15s",
      "2m 25s",
      "15s",
      "58m 44s",
      "35m 24s",
      "12m 44s",
      "1m 14s",
      "35s"
    ]
  },
  "pc": {
    "on": ["54s", "15m 55s", "15m 55s", "3h 33m 45s", "1h 23m 44s", "27m 35s"],
    "off": [
      "1h 9m 49s",
      "7h 38m 25s",
      "7m 35s",
      "35m 35s",
      "1h 11m 35s",
      "2h 55m 25s",
      "38m 4s"
    ]
  }
}
